{
  "portfolio_value": 43506.000244140625,
  "params": {
    "window_days": 750,
    "scenarios": 20000
  },
  "flags": {
    "mode": "t",
    "df": 6,
    "horizon": 1,
    "rho_stress": 0.0,
    "drift": "0",
    "seed": null,
    "ci_level": null,
    "liq_haircut_bp": 0.0
  },
  "VaR": {
    "95": 878.1975192985626,
    "99": 1386.083660088746
  },
  "CVaR": {
    "95": 1211.0242349693156,
    "99": 1791.7692473941113
  },
  "as_pct_of_portfolio": {
    "VaR95_pct": 2.0185664376647403,
    "VaR99_pct": 3.185959757988608
  },
  "current_prices": {
    "RELIANCE.NS": 1377.9000244140625,
    "TCS.NS": 2998.5,
    "HDFCBANK.NS": 978.0
  },
  "daily_volatility": {
    "RELIANCE.NS": 0.015333316520208355,
    "TCS.NS": 0.01369673673997223,
    "HDFCBANK.NS": 0.014347075563942338
  },
  "liquidity": {
    "haircut_bp": 0.0,
    "haircut_abs": 0.0
  },
  "stress_all_down": [
    {
      "Shock": "-1\u03c3 all assets",
      "P&L": -626.073041582704
    },
    {
      "Shock": "-2\u03c3 all assets",
      "P&L": -1252.146083165408
    },
    {
      "Shock": "-3\u03c3 all assets",
      "P&L": -1878.2191247481123
    }
  ],
  "multi_horizon": [
    {
      "horizon_days": 1,
      "VaR95": 887.2717936136563,
      "CVaR95": 1241.3177274104976,
      "VaR99": 1438.2772428147807,
      "CVaR99": 1835.6334852450702
    },
    {
      "horizon_days": 5,
      "VaR95": 1964.8665542190863,
      "CVaR95": 2747.4322057913123,
      "VaR99": 3147.7108302931124,
      "CVaR99": 4021.98080143995
    },
    {
      "horizon_days": 10,
      "VaR95": 2784.73512470295,
      "CVaR95": 3866.905027594736,
      "VaR99": 4572.045713971995,
      "CVaR99": 5734.232698338924
    },
    {
      "horizon_days": 20,
      "VaR95": 3909.020228169607,
      "CVaR95": 5474.298937780671,
      "VaR99": 6369.003818196887,
      "CVaR99": 8165.566158123372
    }
  ],
  "backtest": {
    "alpha": 0.95,
    "n_obs": 484,
    "breaches": 17,
    "hit_rate_pct": 3.512396694214876,
    "kupiec": {
      "LR": 2.505424917769801,
      "p_value": 0.11345487986962736
    },
    "christoffersen": {
      "LR": 2.2746990421468922,
      "p_value": 0.13150064978279066
    },
    "basel_zone_99": "N/A (Basel uses 99%)"
  }
}